<?xml version="1.0" encoding="UTF-8"?>
<GenRun Id="impl_1" LaunchPart="xc7k70tfbv676-1" LaunchTime="1660925356">
  <File Type="ROUTE-STATUS-PB" Name="neander_route_status.pb"/>
  <File Type="PA-TCL" Name="neander.tcl"/>
  <File Type="OPT-DCP" Name="neander_opt.dcp"/>
  <File Type="INIT-TIMING" Name="neander_timing_summary_init.rpt"/>
  <File Type="OPT-METHODOLOGY-DRC" Name="neander_methodology_drc_opted.rpt"/>
  <File Type="RDI-RDI" Name="neander.vdi"/>
  <File Type="PWROPT-DRC" Name="neander_drc_pwropted.rpt"/>
  <File Type="OPT-DRC" Name="neander_drc_opted.rpt"/>
  <File Type="PWROPT-DCP" Name="neander_pwropt.dcp"/>
  <File Type="OPT-HWDEF" Name="neander.hwdef"/>
  <File Type="OPT-TIMING" Name="neander_timing_summary_opted.rpt"/>
  <File Type="PWROPT-TIMING" Name="neander_timing_summary_pwropted.rpt"/>
  <File Type="PLACE-DCP" Name="neander_placed.dcp"/>
  <File Type="PLACE-IO" Name="neander_io_placed.rpt"/>
  <File Type="PLACE-CLK" Name="neander_clock_utilization_placed.rpt"/>
  <File Type="PLACE-UTIL" Name="neander_utilization_placed.rpt"/>
  <File Type="PLACE-UTIL-PB" Name="neander_utilization_placed.pb"/>
  <File Type="PLACE-CTRL" Name="neander_control_sets_placed.rpt"/>
  <File Type="PLACE-SIMILARITY" Name="neander_incremental_reuse_placed.rpt"/>
  <File Type="PLACE-PRE-SIMILARITY" Name="neander_incremental_reuse_pre_placed.rpt"/>
  <File Type="PLACE-TIMING" Name="neander_timing_summary_placed.rpt"/>
  <File Type="POSTPLACE-PWROPT-DCP" Name="neander_postplace_pwropt.dcp"/>
  <File Type="POSTPLACE-PWROPT-TIMING" Name="neander_timing_summary_postplace_pwropted.rpt"/>
  <File Type="PHYSOPT-DCP" Name="neander_physopt.dcp"/>
  <File Type="PHYSOPT-DRC" Name="neander_drc_physopted.rpt"/>
  <File Type="PHYSOPT-TIMING" Name="neander_timing_summary_physopted.rpt"/>
  <File Type="ROUTE-DCP" Name="neander_routed.dcp"/>
  <File Type="ROUTE-BLACKBOX-DCP" Name="neander_routed_bb.dcp"/>
  <File Type="ROUTE-DRC" Name="neander_drc_routed.rpt"/>
  <File Type="ROUTE-DRC-PB" Name="neander_drc_routed.pb"/>
  <File Type="ROUTE-METHODOLOGY-DRC" Name="neander_methodology_drc_routed.rpt"/>
  <File Type="ROUTE-METHODOLOGY-DRC-PB" Name="neander_methodology_drc_routed.pb"/>
  <File Type="BG-BIT" Name="neander.bit"/>
  <File Type="ROUTE-PWR" Name="neander_power_routed.rpt"/>
  <File Type="ROUTE-PWR-SUM" Name="neander_power_summary_routed.pb"/>
  <File Type="ROUTE-PWR-RPX" Name="neander_power_routed.rpx"/>
  <File Type="ROUTE-STATUS" Name="neander_route_status.rpt"/>
  <File Type="ROUTE-TIMINGSUMMARY" Name="neander_timing_summary_routed.rpt"/>
  <File Type="ROUTE-TIMING-PB" Name="neander_timing_summary_routed.pb"/>
  <File Type="ROUTE-TIMING-RPX" Name="neander_timing_summary_routed.rpx"/>
  <File Type="ROUTE-SIMILARITY" Name="neander_incremental_reuse_routed.rpt"/>
  <File Type="ROUTE-CLK" Name="neander_clock_utilization_routed.rpt"/>
  <File Type="POSTROUTE-PHYSOPT-DCP" Name="neander_postroute_physopt.dcp"/>
  <File Type="POSTROUTE-PHYSOPT-BLACKBOX-DCP" Name="neander_postroute_physopt_bb.dcp"/>
  <File Type="POSTROUTE-PHYSOPT-TIMING" Name="neander_timing_summary_postroute_physopted.rpt"/>
  <File Type="POSTROUTE-PHYSOPT-TIMING-PB" Name="neander_timing_summary_postroute_physopted.pb"/>
  <File Type="POSTROUTE-PHYSOPT-TIMING-RPX" Name="neander_timing_summary_postroute_physopted.rpx"/>
  <File Type="BG-BIN" Name="neander.bin"/>
  <File Type="BITSTR-MSK" Name="neander.msk"/>
  <File Type="BITSTR-RBT" Name="neander.rbt"/>
  <File Type="BITSTR-NKY" Name="neander.nky"/>
  <File Type="BITSTR-BMM" Name="neander_bd.bmm"/>
  <File Type="BITSTR-MMI" Name="neander.mmi"/>
  <File Type="BITSTR-SYSDEF" Name="neander.sysdef"/>
  <File Type="BG-BGN" Name="neander.bgn"/>
  <File Type="BG-DRC" Name="neander.drc"/>
  <File Type="WBT-USG" Name="usage_statistics_webtalk.html"/>
  <FileSet Name="sources" Type="DesignSrcs" RelSrcDir="$PSRCDIR/sources_1">
    <Filter Type="Srcs"/>
    <File Path="$PSRCDIR/sources_1/new/neander.vhd">
      <FileInfo>
        <Attr Name="ImportPath" Val="$PPRDIR/../../trabalho_1/trabalho_1.srcs/sources_1/new/neander.vhd"/>
        <Attr Name="ImportTime" Val="1660797562"/>
        <Attr Name="UsedIn" Val="synthesis"/>
        <Attr Name="UsedIn" Val="simulation"/>
      </FileInfo>
    </File>
    <Config>
      <Option Name="DesignMode" Val="RTL"/>
      <Option Name="TopModule" Val="neander"/>
      <Option Name="TopAutoSet" Val="TRUE"/>
    </Config>
  </FileSet>
  <FileSet Name="constrs_in" Type="Constrs" RelSrcDir="$PSRCDIR/constrs_1">
    <Filter Type="Constrs"/>
    <Config>
      <Option Name="ConstrsType" Val="XDC"/>
    </Config>
  </FileSet>
  <Strategy Version="1" Minor="2">
    <StratHandle Name="Vivado Implementation Defaults" Flow="Vivado Implementation 2016"/>
    <Step Id="init_design"/>
    <Step Id="opt_design"/>
    <Step Id="power_opt_design"/>
    <Step Id="place_design"/>
    <Step Id="post_place_power_opt_design"/>
    <Step Id="phys_opt_design"/>
    <Step Id="route_design"/>
    <Step Id="post_route_phys_opt_design"/>
    <Step Id="write_bitstream"/>
  </Strategy>
</GenRun>
